cpc.units-0.1.3-py3.6-nspkg.pth
cpc/units/__init__.py
cpc/units/units.py
cpc.units-0.1.3.dist-info/DESCRIPTION.rst
cpc.units-0.1.3.dist-info/METADATA
cpc.units-0.1.3.dist-info/RECORD
cpc.units-0.1.3.dist-info/WHEEL
cpc.units-0.1.3.dist-info/metadata.json
cpc.units-0.1.3.dist-info/namespace_packages.txt
cpc.units-0.1.3.dist-info/top_level.txt
