Metadata-Version: 2.0
Name: cpc.units
Version: 0.1.3
Summary: CPC Unit Conversion
Home-page: https://github.com/mikecharles/cpc.units
Author: Mike Charles
Author-email: mike.charles@noaa.gov
License: CC
Keywords: cpc.units
Platform: UNKNOWN
Classifier: Development Status :: 1 - Planning
Classifier: Environment :: Console
Classifier: Intended Audience :: Science/Research
Classifier: Programming Language :: Python
Classifier: Programming Language :: Python :: 3
Classifier: Operating System :: OS Independent
Classifier: Topic :: Scientific/Engineering :: Atmospheric Science
Classifier: License :: CC0 1.0 Universal (CC0 1.0) Public Domain Dedication
Requires-Dist: numpy
